mag_manip.libs/libyaml-cpp-f66d14f7.so.0.7.0
mag_manip.libs/libmag_manip-ad6d1872.so
mag_manip/mag_manip.py
mag_manip/_mag_manip.so
mag_manip-3.0.0.dist-info/METADATA
mag_manip-3.0.0.dist-info/top_level.txt
mag_manip-3.0.0.dist-info/RECORD
mag_manip-3.0.0.dist-info/WHEEL
